{"type":"FeatureCollection","features":[{"type":"Feature","properties":{"Name":"Luoyang"},"geometry":{"type":"Point","coordinates":[112.45056152343749,34.610605760914666]}},{"type":"Feature","properties":{"Name":"Jianye"},"geometry":{"type":"Point","coordinates":[118.77319335937499,32.03136328493756]}},{"type":"Feature","properties":{"Name":"Chengdu"},"geometry":{"type":"Point","coordinates":[104.1064453125,30.581179257386985]}}]}